nv21/__init__.py
nv21/conversion.py
nv21-1.0.0.dist-info/LICENSE.txt
nv21-1.0.0.dist-info/METADATA
nv21-1.0.0.dist-info/WHEEL
nv21-1.0.0.dist-info/top_level.txt
nv21-1.0.0.dist-info/RECORD
