Metadata-Version: 2.1
Name: nv21
Version: 1.0.0
Summary: Functions for reading and decoding the data of frames in NV21 format.
Home-page: https://github.com/denisovap2013/nv21
Author: Andrey Denisov
License: UNKNOWN
Project-URL: Bug Reports, https://github.com/denisovap2013/nv21/issues
Project-URL: Source, https://github.com/denisovap2013/nv21/
Keywords: nv21,yuv420sp,yuv
Platform: UNKNOWN
Classifier: Topic :: Scientific/Engineering :: Image Processing
Classifier: Development Status :: 5 - Production/Stable
Classifier: License :: OSI Approved :: MIT License
Classifier: Programming Language :: Python :: 3
Classifier: Programming Language :: Python :: 3.6
Classifier: Programming Language :: Python :: 3.7
Classifier: Programming Language :: Python :: 3.8
Classifier: Programming Language :: Python :: 3.9
Classifier: Programming Language :: Python :: 3 :: Only
Requires-Python: >=3.6, <4
Requires-Dist: opencv-python
Requires-Dist: numpy
